{
  "db_name": "PostgreSQL",
  "query": "select\n    number,\n    payload\nfrom external_blocks\nwhere number >= $1 and number <= $2\norder by number asc;",
  "describe": {
    "columns": [
      {
        "ordinal": 0,
        "name": "number",
        "type_info": "Int8"
      },
      {
        "ordinal": 1,
        "name": "payload",
        "type_info": "Jsonb"
      }
    ],
    "parameters": {
      "Left": [
        "Int8",
        "Int8"
      ]
    },
    "nullable": [
      false,
      false
    ]
  },
  "hash": "7b2ac3def8684e5632dfaee892828d2722aa7376641095063b605ce48dd5e8b3"
}
